MANIFEST.in
setup.cfg
setup.py
versioneer.py
voeventdb/__init__.py
voeventdb.remote.egg-info/PKG-INFO
voeventdb.remote.egg-info/SOURCES.txt
voeventdb.remote.egg-info/dependency_links.txt
voeventdb.remote.egg-info/requires.txt
voeventdb.remote.egg-info/top_level.txt
voeventdb/remote/__init__.py
voeventdb/remote/_version.py
voeventdb/remote/definitions.py
voeventdb/remote/helpers.py
voeventdb/remote/request_wrappers.py
voeventdb/remote/utils.py
voeventdb/remote/apiv1/__init__.py
voeventdb/remote/apiv1/convenience.py
voeventdb/remote/apiv1/definitions.py
voeventdb/remote/apiv1/endpoints.py