Metadata-Version: 1.0
Name: voeventdb.remote
Version: 1.1.0
Summary: Client-library for remotely querying the voeventdb REST API.
Home-page: https://github.com/timstaley/voeventdb.remote
Author: Tim Staley
Author-email: timstaley337@gmail.com
License: UNKNOWN
Platform: UNKNOWN
